umicp/__init__.py
umicp/compression.py
umicp/discovery.py
umicp/envelope.py
umicp/error.py
umicp/events.py
umicp/matrix.py
umicp/pool.py
umicp/py.typed
umicp/tool_discovery.py
umicp/types.py
umicp/peer/__init__.py
umicp/peer/connection.py
umicp/peer/handshake.py
umicp/peer/info.py
umicp/peer/websocket_peer.py
umicp/transport/__init__.py
umicp/transport/http_client.py
umicp/transport/http_server.py
umicp/transport/websocket_client.py
umicp/transport/websocket_server.py
umicp_python-0.2.0.dist-info/licenses/LICENSE
umicp_python-0.2.0.dist-info/METADATA
umicp_python-0.2.0.dist-info/WHEEL
umicp_python-0.2.0.dist-info/top_level.txt
umicp_python-0.2.0.dist-info/RECORD
