Metadata-Version: 2.4
Name: umicp-python
Version: 0.2.0
Summary: Python bindings for the Universal Matrix Inter-Communication Protocol (UMICP) with native type support and tool discovery
Author-email: HiveLLM AI Collaborative Team <team@hivellm.org>
License: MIT
Project-URL: Homepage, https://github.com/hivellm/umicp
Project-URL: Documentation, https://github.com/hivellm/umicp/tree/main/bindings/python/docs
Project-URL: Repository, https://github.com/hivellm/umicp
Project-URL: Issues, https://github.com/hivellm/umicp/issues
Keywords: umicp,communication,matrix,federated-learning,ai,websocket,http2
Classifier: Development Status :: 4 - Beta
Classifier: Intended Audience :: Developers
Classifier: License :: OSI Approved :: MIT License
Classifier: Programming Language :: Python :: 3
Classifier: Programming Language :: Python :: 3.9
Classifier: Programming Language :: Python :: 3.10
Classifier: Programming Language :: Python :: 3.11
Classifier: Programming Language :: Python :: 3.12
Classifier: Topic :: Software Development :: Libraries :: Python Modules
Classifier: Topic :: Scientific/Engineering :: Artificial Intelligence
Classifier: Topic :: System :: Networking
Requires-Python: >=3.9
License-File: LICENSE
Requires-Dist: pydantic>=2.0.0
Requires-Dist: numpy>=1.24.0
Requires-Dist: aiohttp>=3.9.0
Requires-Dist: websockets>=12.0
Requires-Dist: httpx>=0.27.0
Requires-Dist: python-dateutil>=2.8.0
Provides-Extra: dev
Requires-Dist: pytest>=7.4.0; extra == "dev"
Requires-Dist: pytest-asyncio>=0.21.0; extra == "dev"
Requires-Dist: pytest-cov>=4.1.0; extra == "dev"
Requires-Dist: black>=23.0.0; extra == "dev"
Requires-Dist: mypy>=1.5.0; extra == "dev"
Requires-Dist: ruff>=0.1.0; extra == "dev"
Dynamic: license-file
